functions_by_darimco/math_functions.py
functions_by_darimco-0.3.0.dist-info/WHEEL
functions_by_darimco-0.3.0.dist-info/METADATA
functions_by_darimco-0.3.0.dist-info/RECORD
